<?xml version="1.0" encoding="iso-8859-1"?>

<!-- 
  Please see the license.html file included with this distribution for 
  attribution and copyright information.
-->

<root>
	<windowclass name="charsheet" merge="join">
		<sheetdata>

			<sub_charsheet name="notes">
				<class>charsheet_notes_and_logs</class>
			</sub_charsheet>
			<sub_charsheet name="logs">
				<class>charsheet_cohorts</class>
			</sub_charsheet>

			<tabs_charsheet name="tabs">
				<script>
					function onInit()
						if tab and type(tab) == "table" then
							for index,tabInfo in ipairs(tab) do
								if (type(tabInfo) == "table") and (tabInfo.subwindow[1] == "logs") then
									tabInfo.icon[1] = "tab_cohorts";
								end
							end
						end

						super.onInit();
					end
				</script>
			</tabs_charsheet>
		</sheetdata>
	</windowclass>
</root>
